sonar_sdk/__init__.py
sonar_sdk/checks.py
sonar_sdk/client.py
sonar_sdk/connection.py
sonar_sdk/dns.py
sonar_sdk/http.py
sonar_sdk/icmp.py
sonar_sdk/sslcert.py
sonar_sdk/system.py
sonar_sdk/tcp.py
sonar_sdk-0.1.0.dist-info/licenses/LICENSE
sonar_sdk-0.1.0.dist-info/METADATA
sonar_sdk-0.1.0.dist-info/WHEEL
sonar_sdk-0.1.0.dist-info/top_level.txt
sonar_sdk-0.1.0.dist-info/RECORD
