Metadata-Version: 2.4
Name: sonar-sdk
Version: 0.1.0
Summary: Python API Client for Sonar (Constellix) API
Author-email: Shane Barbetta <shane@barbetta.me>
License: MIT
Project-URL: Homepage, https://github.com/sbarbett/sonar-sdk
Project-URL: Documentation, https://github.com/sbarbett/sonar-sdk
Project-URL: Source, https://github.com/sbarbett/sonar-sdk
Project-URL: Issues, https://github.com/sbarbett/sonar-sdk/issues
Keywords: sonar,constellix,dns,api,client
Classifier: Development Status :: 4 - Beta
Classifier: Intended Audience :: Developers
Classifier: License :: OSI Approved :: MIT License
Classifier: Programming Language :: Python :: 3
Classifier: Programming Language :: Python :: 3.8
Classifier: Programming Language :: Python :: 3.9
Classifier: Programming Language :: Python :: 3.10
Classifier: Programming Language :: Python :: 3.11
Classifier: Programming Language :: Python :: 3.12
Requires-Python: >=3.8
License-File: LICENSE
Requires-Dist: requests>=2.26.0
Dynamic: license-file
